Blauwal3_Text-1.6.0-py3.10-nspkg.pth
orangecontrib/text/__init__.py
orangecontrib/text/annotate_documents.py
orangecontrib/text/concave_hull.py
orangecontrib/text/corpus.py
orangecontrib/text/corpus_to_network.py
orangecontrib/text/country_codes.py
orangecontrib/text/guardian.py
orangecontrib/text/i18n_config.py
orangecontrib/text/import_documents.py
orangecontrib/text/language.py
orangecontrib/text/nyt.py
orangecontrib/text/ontology.py
orangecontrib/text/pubmed.py
orangecontrib/text/semantic_search.py
orangecontrib/text/stats.py
orangecontrib/text/tweet_profiler.py
orangecontrib/text/twitter.py
orangecontrib/text/util.py
orangecontrib/text/version.py
orangecontrib/text/wikipedia_api.py
orangecontrib/text/datasets/20newsgroups-test.tab
orangecontrib/text/datasets/20newsgroups-test.tab.metadata
orangecontrib/text/datasets/20newsgroups-train.tab
orangecontrib/text/datasets/20newsgroups-train.tab.metadata
orangecontrib/text/datasets/README.txt
orangecontrib/text/datasets/andersen.tab
orangecontrib/text/datasets/andersen.tab.metadata
orangecontrib/text/datasets/book-excerpts.tab
orangecontrib/text/datasets/book-excerpts.tab.metadata
orangecontrib/text/datasets/deerwester.tab
orangecontrib/text/datasets/deerwester.tab.metadata
orangecontrib/text/datasets/election-tweets-2016.tab
orangecontrib/text/datasets/election-tweets-2016.tab.metadata
orangecontrib/text/datasets/friends-transcripts.tab
orangecontrib/text/datasets/friends-transcripts.tab.metadata
orangecontrib/text/datasets/grimm-tales-selected.tab
orangecontrib/text/datasets/grimm-tales-selected.tab.metadata
orangecontrib/text/datasets/grimm-tales.tab
orangecontrib/text/datasets/grimm-tales.tab.metadata
orangecontrib/text/datasets/reuters-r52-test.tab
orangecontrib/text/datasets/reuters-r52-test.tab.metadata
orangecontrib/text/datasets/reuters-r52-train.tab
orangecontrib/text/datasets/reuters-r52-train.tab.metadata
orangecontrib/text/datasets/reuters-r8-test.tab
Blauwal3_Text-1.6.0.dist-info/LICENSE
Blauwal3_Text-1.6.0.dist-info/METADATA
Blauwal3_Text-1.6.0.dist-info/WHEEL
Blauwal3_Text-1.6.0.dist-info/entry_points.txt
Blauwal3_Text-1.6.0.dist-info/namespace_packages.txt
Blauwal3_Text-1.6.0.dist-info/top_level.txt
Blauwal3_Text-1.6.0.dist-info/RECORD
