Metadata-Version: 2.1
Name: Blauwal3-Text
Version: 1.6.0
Summary: 用于文本挖掘的蓝鲸附加组件。
Home-page: https://github.com/biolab/orange3-text
Download-URL: https://github.com/biolab/orange3-text/tarball/1.16.0
Author: 大圣实验楼
Author-email: dashenglab@163.com
Keywords: orange3-text,data mining,orange3 add-on
License-File: LICENSE
Requires-Dist: Blauwal3>=3.35.0
Requires-Dist: Blauwal3-canvas-core
Requires-Dist: Blauwal3-widget-base
Requires-Dist: anyqt
Requires-Dist: beautifulsoup4
Requires-Dist: biopython
Requires-Dist: conllu
Requires-Dist: docx2txt>=0.6
Requires-Dist: gensim!=4.3.1,>=4.3.0
Requires-Dist: httpx!=0.23.1
Requires-Dist: langdetect
Requires-Dist: lemmagen3
Requires-Dist: nltk>=3.0.5
Requires-Dist: numpy
Requires-Dist: odfpy==1.4.1
Requires-Dist: owlready2
Requires-Dist: pandas
Requires-Dist: pdfminer3k>=1.3.4
Requires-Dist: pypdf
Requires-Dist: pyqtgraph
Requires-Dist: pyyaml
Requires-Dist: requests
Requires-Dist: scikit-learn
Requires-Dist: scipy
Requires-Dist: serverfiles
Requires-Dist: shapely>=2.0
Requires-Dist: simhash>=2.1.1
Requires-Dist: six
Requires-Dist: trimesh>=3.9.8
Requires-Dist: tweepy>=4.0.0
Requires-Dist: ufal.udpipe==1.2.0.3
Requires-Dist: wikipedia
Requires-Dist: yake
Provides-Extra: doc
Requires-Dist: sphinx; extra == "doc"
Requires-Dist: recommonmark; extra == "doc"
Requires-Dist: sphinx-rtd-theme; extra == "doc"
Requires-Dist: docutils; extra == "doc"
Provides-Extra: test
Requires-Dist: coverage; extra == "test"
